cache/__init__.py
cache/cog.py
ipc/__init__.py
ipc/base.py
ipc/client.py
ipc/cog.py
ipc/handlers.py
ipc/server.py
kasushi-0.1.2.dist-info/LICENSE
kasushi-0.1.2.dist-info/METADATA
kasushi-0.1.2.dist-info/WHEEL
kasushi-0.1.2.dist-info/top_level.txt
kasushi-0.1.2.dist-info/RECORD
