Metadata-Version: 2.1
Name: kasushi
Version: 0.1.2
Summary: Building blocks and utility extensions for discord.py bots
Home-page: https://github.com/paris-ci/kasushi
Author: paris-ci
Author-email: site-pipy@api-d.com
License: UNKNOWN
Project-URL: Bug Tracker, https://github.com/paris-ci/kasushi/issues
Platform: UNKNOWN
Classifier: Programming Language :: Python :: 3.8
Classifier: Programming Language :: Python :: 3.9
Classifier: Programming Language :: Python :: 3.10
Classifier: License :: OSI Approved :: MIT License
Classifier: Operating System :: OS Independent
Classifier: Development Status :: 2 - Pre-Alpha
Classifier: Intended Audience :: Developers
Classifier: Topic :: Communications :: Chat
Classifier: Topic :: Software Development :: Libraries :: Python Modules
Classifier: Typing :: Typed
Requires-Python: >=3.8
License-File: LICENSE
